EasyFTP/EasyFTP.py
EasyFTP/Filter.py
EasyFTP/__init__.py
EasyFTP-0.0.33b0.dist-info/LICENSE
EasyFTP-0.0.33b0.dist-info/METADATA
EasyFTP-0.0.33b0.dist-info/WHEEL
EasyFTP-0.0.33b0.dist-info/top_level.txt
EasyFTP-0.0.33b0.dist-info/RECORD
