Metadata-Version: 2.1
Name: EasyFTP
Version: 0.0.33b0
Summary: Easy usage of FTP operation
Home-page: https://github.com/ZustFancake/EasyFTP
Author: ZustFancake
Author-email: ZustFancake@dimigo.hs.kr
Keywords: zustfancake,ftp,easyftp,EasyFTP,pypi
Classifier: Programming Language :: Python :: 3.6
Classifier: Programming Language :: Python :: 3.7
Classifier: Programming Language :: Python :: 3.8
Classifier: Programming Language :: Python :: 3.9
Classifier: Programming Language :: Python :: 3.10
Classifier: Programming Language :: Python :: 3.11
Classifier: Programming Language :: Python :: 3.12
Requires-Python: >=3.6
License-File: LICENSE
Requires-Dist: wheel
